{"v":"5.5.9","fr":25,"ip":0,"op":50,"w":300,"h":300,"nm":"Comp 1","ddd":0,"assets":[{"id":"comp_0","layers":[{"ddd":0,"ind":1,"ty":4,"nm":"Rectangle","sr":1,"ks":{"o":{"a":0,"k":100,"ix":11},"r":{"a":0,"k":0,"ix":10},"p":{"a":0,"k":[213.811,197.612,0],"ix":2},"a":{"a":0,"k":[0,0,0],"ix":1},"s":{"a":0,"k":[100,100,100],"ix":6}},"ao":0,"shapes":[{"ty":"gr","it":[{"ty":"rc","d":1,"s":{"a":0,"k":[36.324,3.908],"ix":2},"p":{"a":0,"k":[0,0],"ix":3},"r":{"a":0,"k":1.954,"ix":4},"nm":"Rectangle Path 1","mn":"ADBE Vector Shape - Rect","hd":false},{"ty":"fl","c":{"a":0,"k":[1,1,1,1],"ix":4},"o":{"a":0,"k":100,"ix":5},"r":1,"bm":0,"nm":"Fill 1","mn":"ADBE Vector Graphic - Fill","hd":false},{"ty":"tr","p":{"a":0,"k":[0,0],"ix":2},"a":{"a":0,"k":[0,0],"ix":1},"s":{"a":0,"k":[100,100],"ix":3},"r":{"a":0,"k":0,"ix":6},"o":{"a":0,"k":100,"ix":7},"sk":{"a":0,"k":0,"ix":4},"sa":{"a":0,"k":0,"ix":5},"nm":"Transform"}],"nm":"Rectangle","np":2,"cix":2,"bm":0,"ix":1,"mn":"ADBE Vector Group","hd":false}],"ip":0,"op":225,"st":0,"bm":0},{"ddd":0,"ind":2,"ty":4,"nm":"Rectangle","sr":1,"ks":{"o":{"a":0,"k":100,"ix":11},"r":{"a":0,"k":0,"ix":10},"p":{"a":0,"k":[213.486,190.283,0],"ix":2},"a":{"a":0,"k":[0,0,0],"ix":1},"s":{"a":0,"k":[100,100,100],"ix":6}},"ao":0,"shapes":[{"ty":"gr","it":[{"ty":"rc","d":1,"s":{"a":0,"k":[36.324,3.908],"ix":2},"p":{"a":0,"k":[0,0],"ix":3},"r":{"a":0,"k":1.954,"ix":4},"nm":"Rectangle Path 1","mn":"ADBE Vector Shape - Rect","hd":false},{"ty":"fl","c":{"a":0,"k":[1,1,1,1],"ix":4},"o":{"a":0,"k":100,"ix":5},"r":1,"bm":0,"nm":"Fill 1","mn":"ADBE Vector Graphic - Fill","hd":false},{"ty":"tr","p":{"a":0,"k":[0,0],"ix":2},"a":{"a":0,"k":[0,0],"ix":1},"s":{"a":0,"k":[100,100],"ix":3},"r":{"a":0,"k":0,"ix":6},"o":{"a":0,"k":100,"ix":7},"sk":{"a":0,"k":0,"ix":4},"sa":{"a":0,"k":0,"ix":5},"nm":"Transform"}],"nm":"Rectangle","np":2,"cix":2,"bm":0,"ix":1,"mn":"ADBE Vector Group","hd":false}],"ip":0,"op":225,"st":0,"bm":0},{"ddd":0,"ind":3,"ty":4,"nm":"Rectangle","sr":1,"ks":{"o":{"a":0,"k":100,"ix":11},"r":{"a":0,"k":0,"ix":10},"p":{"a":0,"k":[219.649,208.888,0],"ix":2},"a":{"a":0,"k":[0,0,0],"ix":1},"s":{"a":0,"k":[100,100,100],"ix":6}},"ao":0,"shapes":[{"ty":"gr","it":[{"ty":"rc","d":1,"s":{"a":0,"k":[24.649,9.118],"ix":2},"p":{"a":0,"k":[0,0],"ix":3},"r":{"a":0,"k":4.559,"ix":4},"nm":"Rectangle Path 1","mn":"ADBE Vector Shape - Rect","hd":false},{"ty":"fl","c":{"a":0,"k":[1,1,1,1],"ix":4},"o":{"a":0,"k":100,"ix":5},"r":1,"bm":0,"nm":"Fill 1","mn":"ADBE Vector Graphic - Fill","hd":false},{"ty":"tr","p":{"a":0,"k":[0,0],"ix":2},"a":{"a":0,"k":[0,0],"ix":1},"s":{"a":0,"k":[100,100],"ix":3},"r":{"a":0,"k":0,"ix":6},"o":{"a":0,"k":100,"ix":7},"sk":{"a":0,"k":0,"ix":4},"sa":{"a":0,"k":0,"ix":5},"nm":"Transform"}],"nm":"Rectangle","np":2,"cix":2,"bm":0,"ix":1,"mn":"ADBE Vector Group","hd":false}],"ip":0,"op":225,"st":0,"bm":0},{"ddd":0,"ind":4,"ty":4,"nm":"Rectangle","sr":1,"ks":{"o":{"a":0,"k":100,"ix":11},"r":{"a":0,"k":0,"ix":10},"p":{"a":0,"k":[177.649,200.704,0],"ix":2},"a":{"a":0,"k":[0,0,0],"ix":1},"s":{"a":0,"k":[100,100,100],"ix":6}},"ao":0,"shapes":[{"ty":"gr","it":[{"ty":"rc","d":1,"s":{"a":0,"k":[24.649,24.75],"ix":2},"p":{"a":0,"k":[0,0],"ix":3},"r":{"a":0,"k":5,"ix":4},"nm":"Rectangle Path 1","mn":"ADBE Vector Shape - Rect","hd":false},{"ty":"fl","c":{"a":0,"k":[1,1,1,1],"ix":4},"o":{"a":0,"k":100,"ix":5},"r":1,"bm":0,"nm":"Fill 1","mn":"ADBE Vector Graphic - Fill","hd":false},{"ty":"tr","p":{"a":0,"k":[0,0],"ix":2},"a":{"a":0,"k":[0,0],"ix":1},"s":{"a":0,"k":[100,100],"ix":3},"r":{"a":0,"k":0,"ix":6},"o":{"a":0,"k":100,"ix":7},"sk":{"a":0,"k":0,"ix":4},"sa":{"a":0,"k":0,"ix":5},"nm":"Transform"}],"nm":"Rectangle","np":2,"cix":2,"bm":0,"ix":1,"mn":"ADBE Vector Group","hd":false}],"ip":0,"op":225,"st":0,"bm":0},{"ddd":0,"ind":5,"ty":4,"nm":"Rectangle","sr":1,"ks":{"o":{"a":0,"k":100,"ix":11},"r":{"a":0,"k":0,"ix":10},"p":{"a":0,"k":[198.892,200.217,0],"ix":2},"a":{"a":0,"k":[0,0,0],"ix":1},"s":{"a":0,"k":[100,100,100],"ix":6}},"ao":0,"shapes":[{"ty":"gr","it":[{"ty":"rc","d":1,"s":{"a":0,"k":[79.135,37.776],"ix":2},"p":{"a":0,"k":[0,0],"ix":3},"r":{"a":0,"k":6,"ix":4},"nm":"Rectangle Path 1","mn":"ADBE Vector Shape - Rect","hd":false},{"ty":"fl","c":{"a":0,"k":[0.870588004589,0.921568989754,1,1],"ix":4},"o":{"a":0,"k":100,"ix":5},"r":1,"bm":0,"nm":"Fill 1","mn":"ADBE Vector Graphic - Fill","hd":false},{"ty":"tr","p":{"a":0,"k":[0,0],"ix":2},"a":{"a":0,"k":[0,0],"ix":1},"s":{"a":0,"k":[100,100],"ix":3},"r":{"a":0,"k":0,"ix":6},"o":{"a":0,"k":100,"ix":7},"sk":{"a":0,"k":0,"ix":4},"sa":{"a":0,"k":0,"ix":5},"nm":"Transform"}],"nm":"Rectangle","np":2,"cix":2,"bm":0,"ix":1,"mn":"ADBE Vector Group","hd":false}],"ip":0,"op":225,"st":0,"bm":0},{"ddd":0,"ind":6,"ty":4,"nm":"Rectangle","sr":1,"ks":{"o":{"a":0,"k":100,"ix":11},"r":{"a":0,"k":0,"ix":10},"p":{"a":0,"k":[213.811,197.612,0],"ix":2},"a":{"a":0,"k":[0,0,0],"ix":1},"s":{"a":0,"k":[100,100,100],"ix":6}},"ao":0,"shapes":[{"ty":"gr","it":[{"ty":"rc","d":1,"s":{"a":0,"k":[36.324,3.908],"ix":2},"p":{"a":0,"k":[0,0],"ix":3},"r":{"a":0,"k":1.954,"ix":4},"nm":"Rectangle Path 1","mn":"ADBE Vector Shape - Rect","hd":false},{"ty":"fl","c":{"a":0,"k":[1,1,1,1],"ix":4},"o":{"a":0,"k":100,"ix":5},"r":1,"bm":0,"nm":"Fill 1","mn":"ADBE Vector Graphic - Fill","hd":false},{"ty":"tr","p":{"a":0,"k":[0,0],"ix":2},"a":{"a":0,"k":[0,0],"ix":1},"s":{"a":0,"k":[100,100],"ix":3},"r":{"a":0,"k":0,"ix":6},"o":{"a":0,"k":100,"ix":7},"sk":{"a":0,"k":0,"ix":4},"sa":{"a":0,"k":0,"ix":5},"nm":"Transform"}],"nm":"Rectangle","np":2,"cix":2,"bm":0,"ix":1,"mn":"ADBE Vector Group","hd":false}],"ip":0,"op":225,"st":0,"bm":0},{"ddd":0,"ind":7,"ty":4,"nm":"Rectangle","sr":1,"ks":{"o":{"a":0,"k":100,"ix":11},"r":{"a":0,"k":0,"ix":10},"p":{"a":0,"k":[213.486,190.283,0],"ix":2},"a":{"a":0,"k":[0,0,0],"ix":1},"s":{"a":0,"k":[100,100,100],"ix":6}},"ao":0,"shapes":[{"ty":"gr","it":[{"ty":"rc","d":1,"s":{"a":0,"k":[36.324,3.908],"ix":2},"p":{"a":0,"k":[0,0],"ix":3},"r":{"a":0,"k":1.954,"ix":4},"nm":"Rectangle Path 1","mn":"ADBE Vector Shape - Rect","hd":false},{"ty":"fl","c":{"a":0,"k":[1,1,1,1],"ix":4},"o":{"a":0,"k":100,"ix":5},"r":1,"bm":0,"nm":"Fill 1","mn":"ADBE Vector Graphic - Fill","hd":false},{"ty":"tr","p":{"a":0,"k":[0,0],"ix":2},"a":{"a":0,"k":[0,0],"ix":1},"s":{"a":0,"k":[100,100],"ix":3},"r":{"a":0,"k":0,"ix":6},"o":{"a":0,"k":100,"ix":7},"sk":{"a":0,"k":0,"ix":4},"sa":{"a":0,"k":0,"ix":5},"nm":"Transform"}],"nm":"Rectangle","np":2,"cix":2,"bm":0,"ix":1,"mn":"ADBE Vector Group","hd":false}],"ip":0,"op":225,"st":0,"bm":0},{"ddd":0,"ind":8,"ty":4,"nm":"Rectangle","sr":1,"ks":{"o":{"a":0,"k":100,"ix":11},"r":{"a":0,"k":0,"ix":10},"p":{"a":0,"k":[219.649,208.888,0],"ix":2},"a":{"a":0,"k":[0,0,0],"ix":1},"s":{"a":0,"k":[100,100,100],"ix":6}},"ao":0,"shapes":[{"ty":"gr","it":[{"ty":"rc","d":1,"s":{"a":0,"k":[24.649,9.118],"ix":2},"p":{"a":0,"k":[0,0],"ix":3},"r":{"a":0,"k":4.559,"ix":4},"nm":"Rectangle Path 1","mn":"ADBE Vector Shape - Rect","hd":false},{"ty":"fl","c":{"a":0,"k":[1,1,1,1],"ix":4},"o":{"a":0,"k":100,"ix":5},"r":1,"bm":0,"nm":"Fill 1","mn":"ADBE Vector Graphic - Fill","hd":false},{"ty":"tr","p":{"a":0,"k":[0,0],"ix":2},"a":{"a":0,"k":[0,0],"ix":1},"s":{"a":0,"k":[100,100],"ix":3},"r":{"a":0,"k":0,"ix":6},"o":{"a":0,"k":100,"ix":7},"sk":{"a":0,"k":0,"ix":4},"sa":{"a":0,"k":0,"ix":5},"nm":"Transform"}],"nm":"Rectangle","np":2,"cix":2,"bm":0,"ix":1,"mn":"ADBE Vector Group","hd":false}],"ip":0,"op":225,"st":0,"bm":0},{"ddd":0,"ind":9,"ty":4,"nm":"Rectangle","sr":1,"ks":{"o":{"a":0,"k":100,"ix":11},"r":{"a":0,"k":0,"ix":10},"p":{"a":0,"k":[177.649,200.704,0],"ix":2},"a":{"a":0,"k":[0,0,0],"ix":1},"s":{"a":0,"k":[100,100,100],"ix":6}},"ao":0,"shapes":[{"ty":"gr","it":[{"ty":"rc","d":1,"s":{"a":0,"k":[24.649,24.75],"ix":2},"p":{"a":0,"k":[0,0],"ix":3},"r":{"a":0,"k":5,"ix":4},"nm":"Rectangle Path 1","mn":"ADBE Vector Shape - Rect","hd":false},{"ty":"fl","c":{"a":0,"k":[1,1,1,1],"ix":4},"o":{"a":0,"k":100,"ix":5},"r":1,"bm":0,"nm":"Fill 1","mn":"ADBE Vector Graphic - Fill","hd":false},{"ty":"tr","p":{"a":0,"k":[0,0],"ix":2},"a":{"a":0,"k":[0,0],"ix":1},"s":{"a":0,"k":[100,100],"ix":3},"r":{"a":0,"k":0,"ix":6},"o":{"a":0,"k":100,"ix":7},"sk":{"a":0,"k":0,"ix":4},"sa":{"a":0,"k":0,"ix":5},"nm":"Transform"}],"nm":"Rectangle","np":2,"cix":2,"bm":0,"ix":1,"mn":"ADBE Vector Group","hd":false}],"ip":0,"op":225,"st":0,"bm":0},{"ddd":0,"ind":10,"ty":4,"nm":"Rectangle","sr":1,"ks":{"o":{"a":0,"k":100,"ix":11},"r":{"a":0,"k":0,"ix":10},"p":{"a":0,"k":[198.892,200.217,0],"ix":2},"a":{"a":0,"k":[0,0,0],"ix":1},"s":{"a":0,"k":[100,100,100],"ix":6}},"ao":0,"shapes":[{"ty":"gr","it":[{"ty":"rc","d":1,"s":{"a":0,"k":[79.135,37.776],"ix":2},"p":{"a":0,"k":[0,0],"ix":3},"r":{"a":0,"k":6,"ix":4},"nm":"Rectangle Path 1","mn":"ADBE Vector Shape - Rect","hd":false},{"ty":"fl","c":{"a":0,"k":[0.870588004589,0.921568989754,1,1],"ix":4},"o":{"a":0,"k":100,"ix":5},"r":1,"bm":0,"nm":"Fill 1","mn":"ADBE Vector Graphic - Fill","hd":false},{"ty":"tr","p":{"a":0,"k":[0,0],"ix":2},"a":{"a":0,"k":[0,0],"ix":1},"s":{"a":0,"k":[100,100],"ix":3},"r":{"a":0,"k":0,"ix":6},"o":{"a":0,"k":100,"ix":7},"sk":{"a":0,"k":0,"ix":4},"sa":{"a":0,"k":0,"ix":5},"nm":"Transform"}],"nm":"Rectangle","np":2,"cix":2,"bm":0,"ix":1,"mn":"ADBE Vector Group","hd":false}],"ip":0,"op":225,"st":0,"bm":0}]},{"id":"comp_1","layers":[{"ddd":0,"ind":1,"ty":4,"nm":"Fill 218","sr":1,"ks":{"o":{"a":0,"k":100,"ix":11},"r":{"a":0,"k":0,"ix":10},"p":{"a":0,"k":[93.292,236.735,0],"ix":2},"a":{"a":0,"k":[0,0,0],"ix":1},"s":{"a":0,"k":[100,100,100],"ix":6}},"ao":0,"shapes":[{"ty":"gr","it":[{"ind":0,"ty":"sh","ix":1,"ks":{"a":0,"k":{"i":[[0,0],[0,-2.19],[7.3,-10.24],[1.46,7.31],[2.91,5.12],[-7.29,2.93],[2.92,4.38],[-8.75,-1.46],[-2.18,0],[0,0],[1.46,-2.2]],"o":[[0,0],[0,2.19],[-7.29,10.24],[-1.45,-7.32],[-2.92,-5.12],[7.3,-2.92],[-2.92,-4.39],[0,0],[2.19,0],[0,0],[0,0]],"v":[[7.721,-22.127],[5.531,-19.937],[11.361,17.363],[-13.429,19.563],[-7.589,8.593],[-5.409,-2.387],[-1.759,-11.887],[6.261,-24.327],[10.631,-25.057],[13.331,-20.077],[7.721,-22.127]],"c":false},"ix":2},"nm":"Path 1","mn":"ADBE Vector Shape - Group","hd":false},{"ty":"fl","c":{"a":0,"k":[0.129411995411,0.129411995411,0.129411995411,1],"ix":4},"o":{"a":0,"k":100,"ix":5},"r":1,"bm":0,"nm":"Fill 1","mn":"ADBE Vector Graphic - Fill","hd":false},{"ty":"tr","p":{"a":0,"k":[0,0],"ix":2},"a":{"a":0,"k":[0,0],"ix":1},"s":{"a":0,"k":[100,100],"ix":3},"r":{"a":0,"k":0,"ix":6},"o":{"a":0,"k":100,"ix":7},"sk":{"a":0,"k":0,"ix":4},"sa":{"a":0,"k":0,"ix":5},"nm":"Transform"}],"nm":"Fill 218","np":2,"cix":2,"bm":0,"ix":1,"mn":"ADBE Vector Group","hd":false}],"ip":0,"op":225,"st":0,"bm":0},{"ddd":0,"ind":2,"ty":4,"nm":"Shape Layer 4","sr":1,"ks":{"o":{"a":0,"k":100,"ix":11},"r":{"a":0,"k":0,"ix":10},"p":{"a":0,"k":[180,320,0],"ix":2},"a":{"a":0,"k":[0,0,0],"ix":1},"s":{"a":0,"k":[100,100,100],"ix":6}},"ao":0,"shapes":[{"ty":"gr","it":[{"ind":0,"ty":"sh","ix":1,"ks":{"a":0,"k":{"i":[[0,0],[0,0],[0,0],[0,0],[1.169,2.355]],"o":[[0,0],[0,0],[0,0],[0,0],[-1.532,-3.086]],"v":[[-62.25,-90],[-78.75,-85.75],[-76,-74.75],[-58.188,-81.438],[-62.107,-84.668]],"c":true},"ix":2},"nm":"Path 1","mn":"ADBE Vector Shape - Group","hd":false},{"ty":"fl","c":{"a":0,"k":[0.870588295133,0.294117647059,0.407843167174,1],"ix":4},"o":{"a":0,"k":100,"ix":5},"r":1,"bm":0,"nm":"Fill 1","mn":"ADBE Vector Graphic - Fill","hd":false},{"ty":"tr","p":{"a":0,"k":[0,0],"ix":2},"a":{"a":0,"k":[0,0],"ix":1},"s":{"a":0,"k":[100,100],"ix":3},"r":{"a":0,"k":0,"ix":6},"o":{"a":0,"k":100,"ix":7},"sk":{"a":0,"k":0,"ix":4},"sa":{"a":0,"k":0,"ix":5},"nm":"Transform"}],"nm":"Shape 1","np":3,"cix":2,"bm":0,"ix":1,"mn":"ADBE Vector Group","hd":false}],"ip":0,"op":225,"st":0,"bm":0},{"ddd":0,"ind":3,"ty":4,"nm":"Shape Layer 3","td":1,"sr":1,"ks":{"o":{"a":0,"k":100,"ix":11},"r":{"a":0,"k":0,"ix":10},"p":{"a":0,"k":[180,320,0],"ix":2},"a":{"a":0,"k":[0,0,0],"ix":1},"s":{"a":0,"k":[100,100,100],"ix":6}},"ao":0,"shapes":[{"ty":"gr","it":[{"ind":0,"ty":"sh","ix":1,"ks":{"a":0,"k":{"i":[[0,0],[0,0],[0,0],[0,0],[1.033,2.144]],"o":[[0,0],[0,0],[0,0],[0,0],[-1.263,-2.622]],"v":[[-62.562,-89.125],[-78.5,-84.5],[-75.625,-71.75],[-57.562,-81.375],[-62.283,-84.081]],"c":true},"ix":2},"nm":"Path 1","mn":"ADBE Vector Shape - Group","hd":false},{"ty":"fl","c":{"a":0,"k":[0.870588295133,0.294117647059,0.407843167174,1],"ix":4},"o":{"a":0,"k":100,"ix":5},"r":1,"bm":0,"nm":"Fill 1","mn":"ADBE Vector Graphic - Fill","hd":false},{"ty":"tr","p":{"a":0,"k":[0,0],"ix":2},"a":{"a":0,"k":[0,0],"ix":1},"s":{"a":0,"k":[100,100],"ix":3},"r":{"a":0,"k":0,"ix":6},"o":{"a":0,"k":100,"ix":7},"sk":{"a":0,"k":0,"ix":4},"sa":{"a":0,"k":0,"ix":5},"nm":"Transform"}],"nm":"Shape 2","np":3,"cix":2,"bm":0,"ix":1,"mn":"ADBE Vector Group","hd":false},{"ty":"gr","it":[{"ty":"fl","c":{"a":0,"k":[1,1,1,1],"ix":4},"o":{"a":0,"k":100,"ix":5},"r":1,"bm":0,"nm":"Fill 1","mn":"ADBE Vector Graphic - Fill","hd":false},{"ty":"tr","p":{"a":0,"k":[0,0],"ix":2},"a":{"a":0,"k":[0,0],"ix":1},"s":{"a":0,"k":[100,100],"ix":3},"r":{"a":0,"k":0,"ix":6},"o":{"a":0,"k":100,"ix":7},"sk":{"a":0,"k":0,"ix":4},"sa":{"a":0,"k":0,"ix":5},"nm":"Transform"}],"nm":"Shape 1","np":2,"cix":2,"bm":0,"ix":2,"mn":"ADBE Vector Group","hd":false}],"ip":0,"op":225,"st":0,"bm":0},{"ddd":0,"ind":4,"ty":4,"nm":"Fill 213","tt":1,"sr":1,"ks":{"o":{"a":0,"k":100,"ix":11},"r":{"a":0,"k":0,"ix":10},"p":{"a":0,"k":[111.89,246.76,0],"ix":2},"a":{"a":0,"k":[0,0,0],"ix":1},"s":{"a":0,"k":[100,100,100],"ix":6}},"ao":0,"shapes":[{"ty":"gr","it":[{"ind":0,"ty":"sh","ix":1,"ks":{"a":0,"k":{"i":[[0,0],[0.47,0.67],[0.08,0.12],[1.27,2.28],[0,0],[0,0],[0,0],[-0.28,-0.23],[3.22,0],[0.19,0.05],[2.08,-6.42]],"o":[[-0.44,-0.65],[-0.09,-0.12],[-2.65,-3.82],[0.16,-1.73],[0,0],[0,0],[0.32,0.23],[-2.94,1.01],[-0.31,0],[0,0],[0,0]],"v":[[-3.263,10.487],[-4.633,8.497],[-4.883,8.137],[-11.653,-1.983],[-11.353,-4.833],[2.717,-10.483],[10.757,-8.913],[11.657,-8.223],[-3.583,-4.433],[-4.343,-4.513],[-3.263,10.487]],"c":false},"ix":2},"nm":"Path 1","mn":"ADBE Vector Shape - Group","hd":false},{"ind":1,"ty":"sh","ix":2,"ks":{"a":0,"k":{"i":[[0,0],[-0.09,-0.03],[0,0]],"o":[[0,0],[-0.82,-0.24],[0,0]],"v":[[-5.443,-4.847],[-4.353,-4.517],[-5.443,-4.847]],"c":false},"ix":2},"nm":"Path 2","mn":"ADBE Vector Shape - Group","hd":false},{"ty":"mm","mm":1,"nm":"Merge Paths 1","mn":"ADBE Vector Filter - Merge","hd":false},{"ty":"fl","c":{"a":0,"k":[0.886904001236,0.377692013979,0.559831976891,1],"ix":4},"o":{"a":0,"k":100,"ix":5},"r":1,"bm":0,"nm":"Fill 1","mn":"ADBE Vector Graphic - Fill","hd":false},{"ty":"tr","p":{"a":0,"k":[0,0],"ix":2},"a":{"a":0,"k":[0,0],"ix":1},"s":{"a":0,"k":[100,100],"ix":3},"r":{"a":0,"k":0,"ix":6},"o":{"a":0,"k":100,"ix":7},"sk":{"a":0,"k":0,"ix":4},"sa":{"a":0,"k":0,"ix":5},"nm":"Transform"}],"nm":"Fill 213","np":4,"cix":2,"bm":0,"ix":1,"mn":"ADBE Vector Group","hd":false}],"ip":0,"op":225,"st":0,"bm":0},{"ddd":0,"ind":5,"ty":4,"nm":"Fill 219","sr":1,"ks":{"o":{"a":0,"k":100,"ix":11},"r":{"a":0,"k":0,"ix":10},"p":{"a":0,"k":[132.51,234.266,0],"ix":2},"a":{"a":0,"k":[0,0,0],"ix":1},"s":{"a":0,"k":[100,100,100],"ix":6}},"ao":0,"shapes":[{"ty":"gr","it":[{"ind":0,"ty":"sh","ix":1,"ks":{"a":0,"k":{"i":[[0,0],[8.04,-2.14],[4.02,-1.78],[-3.33,-2.75],[-0.84,0.42],[-1.46,1.46],[1.46,0.73]],"o":[[0,0],[-8.04,2.13],[-0.44,1.91],[6.31,-2.13],[1.46,-0.73],[1.46,-1.46],[-1.46,-0.74]],"v":[[15.738,-7.208],[-7.072,0.612],[-21.432,4.952],[-18.562,12.772],[-4.772,7.622],[21.148,-7.208],[19.048,-12.688]],"c":true},"ix":2},"nm":"Path 1","mn":"ADBE Vector Shape - Group","hd":false},{"ty":"fl","c":{"a":0,"k":[1,0.803921628466,0.635294117647,1],"ix":4},"o":{"a":0,"k":100,"ix":5},"r":1,"bm":0,"nm":"Fill 1","mn":"ADBE Vector Graphic - Fill","hd":false},{"ty":"tr","p":{"a":0,"k":[1.869,-5.542],"ix":2},"a":{"a":0,"k":[0,0],"ix":1},"s":{"a":0,"k":[100,100],"ix":3},"r":{"a":0,"k":3.346,"ix":6},"o":{"a":0,"k":100,"ix":7},"sk":{"a":0,"k":0,"ix":4},"sa":{"a":0,"k":0,"ix":5},"nm":"Transform"}],"nm":"Fill 216","np":2,"cix":2,"bm":0,"ix":1,"mn":"ADBE Vector Group","hd":false}],"ip":0,"op":225,"st":0,"bm":0},{"ddd":0,"ind":6,"ty":4,"nm":"Fill 212","sr":1,"ks":{"o":{"a":0,"k":100,"ix":11},"r":{"a":0,"k":0,"ix":10},"p":{"a":0,"k":[112.743,255.035,0],"ix":2},"a":{"a":0,"k":[0,0,0],"ix":1},"s":{"a":0,"k":[100,100,100],"ix":6}},"ao":0,"shapes":[{"ty":"gr","it":[{"ind":0,"ty":"sh","ix":1,"ks":{"a":0,"k":{"i":[[0,0],[-0.72,1.47],[0,2.2],[-7.29,-0.73],[1.46,-4.39],[-1.46,-7.31],[3.71,-1.93],[2.11,1.58],[0,0]],"o":[[0,0],[0.73,-1.46],[0,-2.19],[7.29,0.73],[-1.46,4.39],[0.91,4.56],[-2.34,1.22],[0,0],[0,0]],"v":[[-4.441,18.811],[-0.071,9.301],[-13.191,-11.909],[-3.711,-22.149],[13.059,-11.909],[13.059,11.501],[5.489,21.421],[-1.791,20.811],[-4.441,18.811]],"c":false},"ix":2},"nm":"Path 1","mn":"ADBE Vector Shape - Group","hd":false},{"ty":"fl","c":{"a":0,"k":[0.870588004589,0.294117987156,0.407842993736,1],"ix":4},"o":{"a":0,"k":100,"ix":5},"r":1,"bm":0,"nm":"Fill 1","mn":"ADBE Vector Graphic - Fill","hd":false},{"ty":"tr","p":{"a":0,"k":[0,0],"ix":2},"a":{"a":0,"k":[0,0],"ix":1},"s":{"a":0,"k":[100,100],"ix":3},"r":{"a":0,"k":0,"ix":6},"o":{"a":0,"k":100,"ix":7},"sk":{"a":0,"k":0,"ix":4},"sa":{"a":0,"k":0,"ix":5},"nm":"Transform"}],"nm":"Fill 212","np":2,"cix":2,"bm":0,"ix":1,"mn":"ADBE Vector Group","hd":false}],"ip":0,"op":225,"st":0,"bm":0},{"ddd":0,"ind":10,"ty":3,"nm":"Fill 208","sr":1,"ks":{"o":{"a":0,"k":100,"ix":11},"r":{"a":0,"k":0,"ix":10},"p":{"a":0,"k":[107.355,219.635,0],"ix":2},"a":{"a":0,"k":[0,0,0],"ix":1},"s":{"a":0,"k":[100,100,100],"ix":6}},"ao":0,"ip":0,"op":225,"st":0,"bm":0},{"ddd":0,"ind":11,"ty":4,"nm":"Fill 207","parent":10,"td":1,"sr":1,"ks":{"o":{"a":0,"k":100,"ix":11},"r":{"a":0,"k":0,"ix":10},"p":{"a":0,"k":[-3.515,1.703,0],"ix":2},"a":{"a":0,"k":[0,0,0],"ix":1},"s":{"a":0,"k":[100,100,100],"ix":6}},"ao":0,"shapes":[{"ty":"gr","it":[{"ind":0,"ty":"sh","ix":1,"ks":{"a":0,"k":{"i":[[0,0],[0.26,0.05],[0.24,-0.14],[0.1,-0.23],[0.03,-0.12],[-0.01,-0.13],[-0.06,0.09],[0,0],[-0.16,0.09],[-0.48,-0.08]],"o":[[-0.16,-0.19],[-0.25,-0.06],[-0.24,0.15],[-0.05,0.12],[-0.01,0.12],[0.08,-0.1],[0,0],[0.13,-0.17],[0.32,-0.21],[0,0]],"v":[[1.025,-0.349],[0.375,-0.719],[-0.415,-0.599],[-0.915,0.011],[-1.015,0.381],[-1.025,0.751],[-0.825,0.451],[-0.635,0.171],[-0.205,-0.239],[1.025,-0.349]],"c":false},"ix":2},"nm":"Path 1","mn":"ADBE Vector Shape - Group","hd":false},{"ty":"fl","c":{"a":0,"k":[0.367453992367,0.275608986616,0.202549993992,1],"ix":4},"o":{"a":0,"k":100,"ix":5},"r":1,"bm":0,"nm":"Fill 1","mn":"ADBE Vector Graphic - Fill","hd":false},{"ty":"tr","p":{"a":0,"k":[0,0],"ix":2},"a":{"a":0,"k":[0,0],"ix":1},"s":{"a":0,"k":[100,100],"ix":3},"r":{"a":0,"k":0,"ix":6},"o":{"a":0,"k":100,"ix":7},"sk":{"a":0,"k":0,"ix":4},"sa":{"a":0,"k":0,"ix":5},"nm":"Transform"}],"nm":"Fill 207","np":2,"cix":2,"bm":0,"ix":1,"mn":"ADBE Vector Group","hd":false}],"ip":0,"op":225,"st":0,"bm":0},{"ddd":0,"ind":12,"ty":4,"nm":"Fill 204","tt":1,"sr":1,"ks":{"o":{"a":0,"k":100,"ix":11},"r":{"a":0,"k":0,"ix":10},"p":{"a":0,"k":[104.99,228.626,0],"ix":2},"a":{"a":0,"k":[0,0,0],"ix":1},"s":{"a":0,"k":[100,100,100],"ix":6}},"ao":0,"shapes":[{"ty":"gr","it":[{"ind":0,"ty":"sh","ix":1,"ks":{"a":0,"k":{"i":[[0,0],[0,0],[0,0],[0,-0.19],[-0.05,-0.24]],"o":[[-1.56,-0.36],[0.79,0.86],[-0.04,0.17],[0,0.22],[0,0]],"v":[[1.63,1.291],[-1.63,-1.289],[1.61,0.081],[1.56,0.611],[1.63,1.291]],"c":false},"ix":2},"nm":"Path 1","mn":"ADBE Vector Shape - Group","hd":false},{"ty":"fl","c":{"a":0,"k":[0.793437004089,0.513571023941,0.490842998028,1],"ix":4},"o":{"a":0,"k":100,"ix":5},"r":1,"bm":0,"nm":"Fill 1","mn":"ADBE Vector Graphic - Fill","hd":false},{"ty":"tr","p":{"a":0,"k":[0,0],"ix":2},"a":{"a":0,"k":[0,0],"ix":1},"s":{"a":0,"k":[100,100],"ix":3},"r":{"a":0,"k":0,"ix":6},"o":{"a":0,"k":100,"ix":7},"sk":{"a":0,"k":0,"ix":4},"sa":{"a":0,"k":0,"ix":5},"nm":"Transform"}],"nm":"Fill 204","np":2,"cix":2,"bm":0,"ix":1,"mn":"ADBE Vector Group","hd":false}],"ip":0,"op":225,"st":0,"bm":0},{"ddd":0,"ind":13,"ty":4,"nm":"Fill 203","sr":1,"ks":{"o":{"a":0,"k":100,"ix":11},"r":{"a":0,"k":0,"ix":10},"p":{"a":0,"k":[103.792,226.51,0],"ix":2},"a":{"a":0,"k":[0,0,0],"ix":1},"s":{"a":0,"k":[100,100,100],"ix":6}},"ao":0,"shapes":[{"ty":"gr","it":[{"ind":0,"ty":"sh","ix":1,"ks":{"a":0,"k":{"i":[[0,0],[0.8,0.86],[-0.5,2.05],[-1.06,2.81],[1.63,0.48],[3.41,-2.76],[-3.68,-0.56],[1.37,-2.13],[-2.13,1.57],[0,0]],"o":[[0,0],[-0.79,-0.85],[0,0],[1.38,-3.67],[-1.63,-0.48],[-3.41,2.76],[0,0],[0,0],[2.12,-1.57],[0,0]],"v":[[9.325,10.779],[5.855,8.519],[2.815,2.199],[7.405,0.729],[0.485,-11.961],[-8.175,-11.891],[-3.005,3.209],[-0.415,11.889],[7.345,12.719],[9.325,10.779]],"c":false},"ix":2},"nm":"Path 1","mn":"ADBE Vector Shape - Group","hd":false},{"ty":"fl","c":{"a":0,"k":[1,0.803921997547,0.635294020176,1],"ix":4},"o":{"a":0,"k":100,"ix":5},"r":1,"bm":0,"nm":"Fill 1","mn":"ADBE Vector Graphic - Fill","hd":false},{"ty":"tr","p":{"a":0,"k":[0,0],"ix":2},"a":{"a":0,"k":[0,0],"ix":1},"s":{"a":0,"k":[100,100],"ix":3},"r":{"a":0,"k":0,"ix":6},"o":{"a":0,"k":100,"ix":7},"sk":{"a":0,"k":0,"ix":4},"sa":{"a":0,"k":0,"ix":5},"nm":"Transform"}],"nm":"Fill 203","np":2,"cix":2,"bm":0,"ix":1,"mn":"ADBE Vector Group","hd":false}],"ip":0,"op":225,"st":0,"bm":0},{"ddd":0,"ind":14,"ty":4,"nm":"Fill 202","sr":1,"ks":{"o":{"a":0,"k":100,"ix":11},"r":{"a":0,"k":0,"ix":10},"p":{"a":0,"k":[103.335,343.07,0],"ix":2},"a":{"a":0,"k":[0,0,0],"ix":1},"s":{"a":0,"k":[100,100,100],"ix":6}},"ao":0,"shapes":[{"ty":"gr","it":[{"ind":0,"ty":"sh","ix":1,"ks":{"a":0,"k":{"i":[[0,0],[0,0],[0,0],[0,0],[0,0]],"o":[[0,0],[0,0],[0,0],[0,0],[0,0]],"v":[[-4.395,-1.589],[2.965,3.551],[4.395,0.601],[-3.445,-3.549],[-4.395,-1.589]],"c":false},"ix":2},"nm":"Path 1","mn":"ADBE Vector Shape - Group","hd":false},{"ty":"fl","c":{"a":0,"k":[0.890609025955,0.405656993389,0.501996994019,1],"ix":4},"o":{"a":0,"k":100,"ix":5},"r":1,"bm":0,"nm":"Fill 1","mn":"ADBE Vector Graphic - Fill","hd":false},{"ty":"tr","p":{"a":0,"k":[0,0],"ix":2},"a":{"a":0,"k":[0,0],"ix":1},"s":{"a":0,"k":[100,100],"ix":3},"r":{"a":0,"k":0,"ix":6},"o":{"a":0,"k":100,"ix":7},"sk":{"a":0,"k":0,"ix":4},"sa":{"a":0,"k":0,"ix":5},"nm":"Transform"}],"nm":"Fill 202","np":2,"cix":2,"bm":0,"ix":1,"mn":"ADBE Vector Group","hd":false}],"ip":0,"op":225,"st":0,"bm":0},{"ddd":0,"ind":15,"ty":4,"nm":"Fill 201","td":1,"sr":1,"ks":{"o":{"a":0,"k":100,"ix":11},"r":{"a":0,"k":0,"ix":10},"p":{"a":0,"k":[133.147,340.309,0],"ix":2},"a":{"a":0,"k":[0,0,0],"ix":1},"s":{"a":0,"k":[100,100,100],"ix":6}},"ao":0,"shapes":[{"ty":"gr","it":[{"ind":0,"ty":"sh","ix":1,"ks":{"a":0,"k":{"i":[[0,0],[0,0],[0,0],[0,0],[0,0]],"o":[[0,0],[0,0],[0,0],[0,0],[0,0]],"v":[[-4.259,1.698],[4.261,1.698],[4.261,-1.702],[-4.259,-0.562],[-4.259,1.698]],"c":false},"ix":2},"nm":"Path 1","mn":"ADBE Vector Shape - Group","hd":false},{"ty":"fl","c":{"a":0,"k":[0.890609025955,0.405656993389,0.501996994019,1],"ix":4},"o":{"a":0,"k":100,"ix":5},"r":1,"bm":0,"nm":"Fill 1","mn":"ADBE Vector Graphic - Fill","hd":false},{"ty":"tr","p":{"a":0,"k":[0,0],"ix":2},"a":{"a":0,"k":[0,0],"ix":1},"s":{"a":0,"k":[100,100],"ix":3},"r":{"a":0,"k":0,"ix":6},"o":{"a":0,"k":100,"ix":7},"sk":{"a":0,"k":0,"ix":4},"sa":{"a":0,"k":0,"ix":5},"nm":"Transform"}],"nm":"Fill 201","np":2,"cix":2,"bm":0,"ix":1,"mn":"ADBE Vector Group","hd":false}],"ip":0,"op":225,"st":0,"bm":0},{"ddd":0,"ind":16,"ty":4,"nm":"Fill 199","tt":1,"sr":1,"ks":{"o":{"a":0,"k":100,"ix":11},"r":{"a":0,"k":0,"ix":10},"p":{"a":0,"k":[125.202,272.279,0],"ix":2},"a":{"a":0,"k":[0,0,0],"ix":1},"s":{"a":0,"k":[100,100,100],"ix":6}},"ao":0,"shapes":[{"ty":"gr","it":[{"ind":0,"ty":"sh","ix":1,"ks":{"a":0,"k":{"i":[[0,0],[0.18,0.12],[-0.09,0],[-0.04,-0.07],[-0.07,-0.15]],"o":[[-0.18,-0.11],[0,-0.12],[0.06,0],[0.07,0.15],[0,0]],"v":[[0.275,0.274],[-0.275,-0.076],[-0.095,-0.276],[0.055,-0.176],[0.275,0.274]],"c":false},"ix":2},"nm":"Path 1","mn":"ADBE Vector Shape - Group","hd":false},{"ty":"fl","c":{"a":0,"k":[0.174134001136,0.185231998563,0.465860009193,1],"ix":4},"o":{"a":0,"k":100,"ix":5},"r":1,"bm":0,"nm":"Fill 1","mn":"ADBE Vector Graphic - Fill","hd":false},{"ty":"tr","p":{"a":0,"k":[0,0],"ix":2},"a":{"a":0,"k":[0,0],"ix":1},"s":{"a":0,"k":[100,100],"ix":3},"r":{"a":0,"k":0,"ix":6},"o":{"a":0,"k":100,"ix":7},"sk":{"a":0,"k":0,"ix":4},"sa":{"a":0,"k":0,"ix":5},"nm":"Transform"}],"nm":"Fill 199","np":2,"cix":2,"bm":0,"ix":1,"mn":"ADBE Vector Group","hd":false}],"ip":0,"op":225,"st":0,"bm":0},{"ddd":0,"ind":17,"ty":4,"nm":"Fill 198","tt":1,"sr":1,"ks":{"o":{"a":0,"k":100,"ix":11},"r":{"a":0,"k":0,"ix":10},"p":{"a":0,"k":[130.125,290.379,0],"ix":2},"a":{"a":0,"k":[0,0,0],"ix":1},"s":{"a":0,"k":[100,100,100],"ix":6}},"ao":0,"shapes":[{"ty":"gr","it":[{"ind":0,"ty":"sh","ix":1,"ks":{"a":0,"k":{"i":[[0,0],[5.7,11.4],[0,0.04],[-0.19,-0.11],[-1.66,-10.61],[-0.12,-1.9]],"o":[[-1.42,-12.74],[-0.02,-0.04],[0.18,0.13],[4.76,9.64],[0.14,1.81],[0,0]],"v":[[5.207,18.179],[-5.173,-18.061],[-5.203,-18.181],[-4.643,-17.821],[4.817,12.589],[5.207,18.179]],"c":false},"ix":2},"nm":"Path 1","mn":"ADBE Vector Shape - Group","hd":false},{"ty":"fl","c":{"a":0,"k":[0.198183998466,0.201542004943,0.489930987358,1],"ix":4},"o":{"a":0,"k":100,"ix":5},"r":1,"bm":0,"nm":"Fill 1","mn":"ADBE Vector Graphic - Fill","hd":false},{"ty":"tr","p":{"a":0,"k":[0,0],"ix":2},"a":{"a":0,"k":[0,0],"ix":1},"s":{"a":0,"k":[100,100],"ix":3},"r":{"a":0,"k":0,"ix":6},"o":{"a":0,"k":100,"ix":7},"sk":{"a":0,"k":0,"ix":4},"sa":{"a":0,"k":0,"ix":5},"nm":"Transform"}],"nm":"Fill 198","np":2,"cix":2,"bm":0,"ix":1,"mn":"ADBE Vector Group","hd":false}],"ip":0,"op":225,"st":0,"bm":0},{"ddd":0,"ind":18,"ty":4,"nm":"Fill 197","tt":1,"sr":1,"ks":{"o":{"a":0,"k":100,"ix":11},"r":{"a":0,"k":0,"ix":10},"p":{"a":0,"k":[106.173,309.32,0],"ix":2},"a":{"a":0,"k":[0,0,0],"ix":1},"s":{"a":0,"k":[100,100,100],"ix":6}},"ao":0,"shapes":[{"ty":"gr","it":[{"ind":0,"ty":"sh","ix":1,"ks":{"a":0,"k":{"i":[[0,0],[0.08,0.04],[-1.71,3.5],[0.43,7.22],[-0.19,6.33],[-1.01,5.76],[-0.11,-0.05],[0.04,-6.73],[-0.27,-3.4],[0.24,-3.37],[2.35,-4.76],[1.91,-3.09]],"o":[[-0.16,-0.06],[2.01,-3.25],[2.96,-6.06],[-0.38,-6.29],[0.17,-5.89],[0.11,0.06],[-1.16,6.59],[-0.03,3.41],[0.26,3.35],[-0.4,5.63],[-1.64,3.32],[0,0]],"v":[[-5.704,32.878],[-6.054,32.728],[-0.454,22.608],[4.726,3.358],[3.906,-15.402],[5.716,-32.882],[6.056,-32.722],[4.216,-12.712],[4.576,-2.492],[5.096,7.598],[-0.364,23.258],[-5.704,32.878]],"c":false},"ix":2},"nm":"Path 1","mn":"ADBE Vector Shape - Group","hd":false},{"ty":"fl","c":{"a":0,"k":[0.198183998466,0.201542004943,0.489930987358,1],"ix":4},"o":{"a":0,"k":100,"ix":5},"r":1,"bm":0,"nm":"Fill 1","mn":"ADBE Vector Graphic - Fill","hd":false},{"ty":"tr","p":{"a":0,"k":[0,0],"ix":2},"a":{"a":0,"k":[0,0],"ix":1},"s":{"a":0,"k":[100,100],"ix":3},"r":{"a":0,"k":0,"ix":6},"o":{"a":0,"k":100,"ix":7},"sk":{"a":0,"k":0,"ix":4},"sa":{"a":0,"k":0,"ix":5},"nm":"Transform"}],"nm":"Fill 197","np":2,"cix":2,"bm":0,"ix":1,"mn":"ADBE Vector Group","hd":false}],"ip":0,"op":225,"st":0,"bm":0},{"ddd":0,"ind":19,"ty":4,"nm":"Fill 196","tt":1,"sr":1,"ks":{"o":{"a":0,"k":100,"ix":11},"r":{"a":0,"k":0,"ix":10},"p":{"a":0,"k":[126.123,268.743,0],"ix":2},"a":{"a":0,"k":[0,0,0],"ix":1},"s":{"a":0,"k":[100,100,100],"ix":6}},"ao":0,"shapes":[{"ty":"gr","it":[{"ind":0,"ty":"sh","ix":1,"ks":{"a":0,"k":{"i":[[0,0],[-0.04,0.19],[-0.18,0.12],[-0.06,-0.13],[0.28,-0.18]],"o":[[0.05,-0.19],[0.18,-0.12],[0.05,0.12],[-0.28,0.18],[0,0]],"v":[[-0.423,0.461],[-0.293,-0.099],[0.257,-0.459],[0.427,-0.079],[-0.423,0.461]],"c":false},"ix":2},"nm":"Path 1","mn":"ADBE Vector Shape - Group","hd":false},{"ty":"fl","c":{"a":0,"k":[0.198183998466,0.201542004943,0.489930987358,1],"ix":4},"o":{"a":0,"k":100,"ix":5},"r":1,"bm":0,"nm":"Fill 1","mn":"ADBE Vector Graphic - Fill","hd":false},{"ty":"tr","p":{"a":0,"k":[0,0],"ix":2},"a":{"a":0,"k":[0,0],"ix":1},"s":{"a":0,"k":[100,100],"ix":3},"r":{"a":0,"k":0,"ix":6},"o":{"a":0,"k":100,"ix":7},"sk":{"a":0,"k":0,"ix":4},"sa":{"a":0,"k":0,"ix":5},"nm":"Transform"}],"nm":"Fill 196","np":2,"cix":2,"bm":0,"ix":1,"mn":"ADBE Vector Group","hd":false}],"ip":0,"op":225,"st":0,"bm":0},{"ddd":0,"ind":20,"ty":4,"nm":"Fill 195","tt":1,"sr":1,"ks":{"o":{"a":0,"k":100,"ix":11},"r":{"a":0,"k":0,"ix":10},"p":{"a":0,"k":[109.309,275.786,0],"ix":2},"a":{"a":0,"k":[0,0,0],"ix":1},"s":{"a":0,"k":[100,100,100],"ix":6}},"ao":0,"shapes":[{"ty":"gr","it":[{"ind":0,"ty":"sh","ix":1,"ks":{"a":0,"k":{"i":[[0,0],[-0.04,0.14],[-0.74,0.18],[0,0],[0.93,-0.17]],"o":[[0.04,-0.16],[0.74,-0.14],[0,0],[-0.91,0.22],[0,0]],"v":[[-1.38,0.464],[-1.26,0.014],[0.95,-0.466],[1.38,-0.136],[-1.38,0.464]],"c":false},"ix":2},"nm":"Path 1","mn":"ADBE Vector Shape - Group","hd":false},{"ty":"fl","c":{"a":0,"k":[0.198183998466,0.201542004943,0.489930987358,1],"ix":4},"o":{"a":0,"k":100,"ix":5},"r":1,"bm":0,"nm":"Fill 1","mn":"ADBE Vector Graphic - Fill","hd":false},{"ty":"tr","p":{"a":0,"k":[0,0],"ix":2},"a":{"a":0,"k":[0,0],"ix":1},"s":{"a":0,"k":[100,100],"ix":3},"r":{"a":0,"k":0,"ix":6},"o":{"a":0,"k":100,"ix":7},"sk":{"a":0,"k":0,"ix":4},"sa":{"a":0,"k":0,"ix":5},"nm":"Transform"}],"nm":"Fill 195","np":2,"cix":2,"bm":0,"ix":1,"mn":"ADBE Vector Group","hd":false}],"ip":0,"op":225,"st":0,"bm":0},{"ddd":0,"ind":21,"ty":4,"nm":"Fill 194","tt":1,"sr":1,"ks":{"o":{"a":0,"k":100,"ix":11},"r":{"a":0,"k":0,"ix":10},"p":{"a":0,"k":[126.479,272.606,0],"ix":2},"a":{"a":0,"k":[0,0,0],"ix":1},"s":{"a":0,"k":[100,100,100],"ix":6}},"ao":0,"shapes":[{"ty":"gr","it":[{"ind":0,"ty":"sh","ix":1,"ks":{"a":0,"k":{"i":[[0,0],[0.97,0.58],[0.07,0.15],[0.06,0],[0,-0.11],[0.19,0.15],[-0.07,0.1],[-1.43,-0.28],[-0.05,-0.15]],"o":[[-1.13,-0.19],[-0.07,-0.15],[-0.04,-0.07],[-0.09,0],[-0.2,-0.13],[0.08,-0.1],[1.16,0.88],[0.06,0.15],[0,0]],"v":[[2.128,1.133],[-1.002,-0.047],[-1.222,-0.507],[-1.372,-0.607],[-1.552,-0.407],[-2.132,-0.827],[-1.902,-1.137],[1.958,0.673],[2.128,1.133]],"c":false},"ix":2},"nm":"Path 1","mn":"ADBE Vector Shape - Group","hd":false},{"ty":"fl","c":{"a":0,"k":[0.198183998466,0.201542004943,0.489930987358,1],"ix":4},"o":{"a":0,"k":100,"ix":5},"r":1,"bm":0,"nm":"Fill 1","mn":"ADBE Vector Graphic - Fill","hd":false},{"ty":"tr","p":{"a":0,"k":[0,0],"ix":2},"a":{"a":0,"k":[0,0],"ix":1},"s":{"a":0,"k":[100,100],"ix":3},"r":{"a":0,"k":0,"ix":6},"o":{"a":0,"k":100,"ix":7},"sk":{"a":0,"k":0,"ix":4},"sa":{"a":0,"k":0,"ix":5},"nm":"Transform"}],"nm":"Fill 194","np":2,"cix":2,"bm":0,"ix":1,"mn":"ADBE Vector Group","hd":false}],"ip":0,"op":225,"st":0,"bm":0},{"ddd":0,"ind":22,"ty":4,"nm":"Fill 193","tt":1,"sr":1,"ks":{"o":{"a":0,"k":100,"ix":11},"r":{"a":0,"k":0,"ix":10},"p":{"a":0,"k":[108.869,279.001,0],"ix":2},"a":{"a":0,"k":[0,0,0],"ix":1},"s":{"a":0,"k":[100,100,100],"ix":6}},"ao":0,"shapes":[{"ty":"gr","it":[{"ind":0,"ty":"sh","ix":1,"ks":{"a":0,"k":{"i":[[0,0],[-0.04,0.16],[-0.79,1.63],[-0.22,0.87],[-0.1,-0.07],[1.09,-1.23],[0.95,-0.21]],"o":[[0.04,-0.16],[1.43,-0.42],[0.39,-0.78],[0.1,0.08],[-0.43,1.67],[-0.76,0.86],[0,0]],"v":[[-2.392,3.154],[-2.282,2.684],[1.188,-0.666],[2.088,-3.156],[2.388,-2.936],[0.218,1.524],[-2.392,3.154]],"c":false},"ix":2},"nm":"Path 1","mn":"ADBE Vector Shape - Group","hd":false},{"ty":"fl","c":{"a":0,"k":[0.198183998466,0.201542004943,0.489930987358,1],"ix":4},"o":{"a":0,"k":100,"ix":5},"r":1,"bm":0,"nm":"Fill 1","mn":"ADBE Vector Graphic - Fill","hd":false},{"ty":"tr","p":{"a":0,"k":[0,0],"ix":2},"a":{"a":0,"k":[0,0],"ix":1},"s":{"a":0,"k":[100,100],"ix":3},"r":{"a":0,"k":0,"ix":6},"o":{"a":0,"k":100,"ix":7},"sk":{"a":0,"k":0,"ix":4},"sa":{"a":0,"k":0,"ix":5},"nm":"Transform"}],"nm":"Fill 193","np":2,"cix":2,"bm":0,"ix":1,"mn":"ADBE Vector Group","hd":false}],"ip":0,"op":225,"st":0,"bm":0},{"ddd":0,"ind":23,"ty":4,"nm":"Fill 191","tt":1,"sr":1,"ks":{"o":{"a":0,"k":100,"ix":11},"r":{"a":0,"k":0,"ix":10},"p":{"a":0,"k":[121.671,305.681,0],"ix":2},"a":{"a":0,"k":[0,0,0],"ix":1},"s":{"a":0,"k":[100,100,100],"ix":6}},"ao":0,"shapes":[{"ty":"gr","it":[{"ind":0,"ty":"sh","ix":1,"ks":{"a":0,"k":{"i":[[0,0],[0,0],[0,0],[-0.95,-0.57],[0.94,-1.14],[0,0],[-0.09,-2.36]],"o":[[-1.55,-4.07],[0,0],[0,0],[0.94,0.57],[-0.95,1.14],[0,0],[0,0]],"v":[[0.946,11.341],[-1.774,4.551],[-0.824,-11.339],[1.066,-3.959],[1.066,0.011],[0.116,5.681],[0.946,11.341]],"c":false},"ix":2},"nm":"Path 1","mn":"ADBE Vector Shape - Group","hd":false},{"ty":"fl","c":{"a":0,"k":[0.167649000883,0.18691599369,0.411994993687,1],"ix":4},"o":{"a":0,"k":100,"ix":5},"r":1,"bm":0,"nm":"Fill 1","mn":"ADBE Vector Graphic - Fill","hd":false},{"ty":"tr","p":{"a":0,"k":[0,0],"ix":2},"a":{"a":0,"k":[0,0],"ix":1},"s":{"a":0,"k":[100,100],"ix":3},"r":{"a":0,"k":0,"ix":6},"o":{"a":0,"k":100,"ix":7},"sk":{"a":0,"k":0,"ix":4},"sa":{"a":0,"k":0,"ix":5},"nm":"Transform"}],"nm":"Fill 191","np":2,"cix":2,"bm":0,"ix":1,"mn":"ADBE Vector Group","hd":false}],"ip":0,"op":225,"st":0,"bm":0},{"ddd":0,"ind":24,"ty":4,"nm":"Fill 190","sr":1,"ks":{"o":{"a":0,"k":100,"ix":11},"r":{"a":0,"k":0,"ix":10},"p":{"a":0,"k":[118.241,305.692,0],"ix":2},"a":{"a":0,"k":[0,0,0],"ix":1},"s":{"a":0,"k":[100,100,100],"ix":6}},"ao":0,"shapes":[{"ty":"gr","it":[{"ind":0,"ty":"sh","ix":1,"ks":{"a":0,"k":{"i":[[0,0],[0,0],[-0.47,-3.97],[0.94,-1.7],[0,0],[0.47,0],[-0.48,6.81],[0,0],[-1.89,-12.49],[0,0],[2.84,12.49],[0,0]],"o":[[0,0],[0,0],[0.47,3.97],[-0.95,1.71],[0,0],[-0.47,0],[0.47,-6.81],[0,0],[0,0],[0,0],[-2.84,-12.48],[0,0]],"v":[[7.332,-39.157],[-9.698,-31.777],[-13.958,-10.217],[-13.008,16.453],[-18.218,36.323],[-12.068,39.153],[0.712,14.753],[1.652,4.543],[11.592,35.753],[18.222,34.613],[14.902,-17.027],[7.332,-39.157]],"c":false},"ix":2},"nm":"Path 1","mn":"ADBE Vector Shape - Group","hd":false},{"ty":"fl","c":{"a":0,"k":[0.129411995411,0.129411995411,0.129411995411,1],"ix":4},"o":{"a":0,"k":100,"ix":5},"r":1,"bm":0,"nm":"Fill 1","mn":"ADBE Vector Graphic - Fill","hd":false},{"ty":"tr","p":{"a":0,"k":[0,0],"ix":2},"a":{"a":0,"k":[0,0],"ix":1},"s":{"a":0,"k":[100,100],"ix":3},"r":{"a":0,"k":0,"ix":6},"o":{"a":0,"k":100,"ix":7},"sk":{"a":0,"k":0,"ix":4},"sa":{"a":0,"k":0,"ix":5},"nm":"Transform"}],"nm":"Fill 190","np":2,"cix":2,"bm":0,"ix":1,"mn":"ADBE Vector Group","hd":false}],"ip":0,"op":225,"st":0,"bm":0},{"ddd":0,"ind":25,"ty":3,"nm":"▽ Group 189","sr":1,"ks":{"o":{"a":0,"k":100,"ix":11},"r":{"a":0,"k":0,"ix":10},"p":{"a":0,"k":[137.361,349.977,0],"ix":2},"a":{"a":0,"k":[8.432,11.724,0],"ix":1},"s":{"a":0,"k":[100,100,100],"ix":6}},"ao":0,"ip":0,"op":225,"st":0,"bm":0},{"ddd":0,"ind":26,"ty":4,"nm":"▨ Clip 189","parent":28,"td":1,"sr":1,"ks":{"o":{"a":0,"k":100,"ix":11},"r":{"a":0,"k":0,"ix":10},"p":{"a":0,"k":[0,0,0],"ix":2},"a":{"a":0,"k":[0,0,0],"ix":1},"s":{"a":0,"k":[100,100,100],"ix":6}},"ao":0,"shapes":[{"ty":"gr","it":[{"ind":0,"ty":"sh","ix":1,"ks":{"a":0,"k":{"i":[[0,0],[0,0],[0.94,-1.13],[0,1.13],[0,0],[0,0],[0,0]],"o":[[0,0],[0,0],[0,0],[0,-1.14],[0,0],[0,0],[0,0]],"v":[[-2.227,-11.066],[-2.227,5.394],[7.713,11.064],[-6.017,9.934],[-5.537,4.824],[-7.767,-10.156],[-2.227,-11.066]],"c":false},"ix":2},"nm":"Path 1","mn":"ADBE Vector Shape - Group","hd":false},{"ty":"tr","p":{"a":0,"k":[0,0],"ix":2},"a":{"a":0,"k":[0,0],"ix":1},"s":{"a":0,"k":[100,100],"ix":3},"r":{"a":0,"k":0,"ix":6},"o":{"a":0,"k":100,"ix":7},"sk":{"a":0,"k":0,"ix":4},"sa":{"a":0,"k":0,"ix":5},"nm":"Transform"}],"nm":"Clip 188","np":1,"cix":2,"bm":0,"ix":1,"mn":"ADBE Vector Group","hd":false},{"ty":"fl","c":{"a":0,"k":[1,0,0,1],"ix":4},"o":{"a":0,"k":100,"ix":5},"r":1,"bm":0,"nm":"Fill 1","mn":"ADBE Vector Graphic - Fill","hd":false}],"ip":0,"op":225,"st":0,"bm":0},{"ddd":0,"ind":27,"ty":4,"nm":"Fill 187","parent":25,"tt":1,"sr":1,"ks":{"o":{"a":0,"k":100,"ix":11},"r":{"a":0,"k":0,"ix":10},"p":{"a":0,"k":[8.477,21.067,0],"ix":2},"a":{"a":0,"k":[0,0,0],"ix":1},"s":{"a":0,"k":[100,100,100],"ix":6}},"ao":0,"shapes":[{"ty":"gr","it":[{"ind":0,"ty":"sh","ix":1,"ks":{"a":0,"k":{"i":[[0,0],[-0.47,-1.13],[0,0],[0,0],[0,0],[0,0],[0,0]],"o":[[0,0],[0.48,1.14],[0,0],[0,0],[0,0],[0,0],[0,0]],"v":[[-6.624,-4.251],[-4.264,-3.691],[-1.424,-5.391],[10.886,-0.281],[6.626,5.389],[-10.884,1.419],[-6.624,-4.251]],"c":false},"ix":2},"nm":"Path 1","mn":"ADBE Vector Shape - Group","hd":false},{"ty":"fl","c":{"a":0,"k":[0.129411995411,0.129411995411,0.129411995411,1],"ix":4},"o":{"a":0,"k":100,"ix":5},"r":1,"bm":0,"nm":"Fill 1","mn":"ADBE Vector Graphic - Fill","hd":false},{"ty":"tr","p":{"a":0,"k":[0,0],"ix":2},"a":{"a":0,"k":[0,0],"ix":1},"s":{"a":0,"k":[100,100],"ix":3},"r":{"a":0,"k":0,"ix":6},"o":{"a":0,"k":100,"ix":7},"sk":{"a":0,"k":0,"ix":4},"sa":{"a":0,"k":0,"ix":5},"nm":"Transform"}],"nm":"Fill 187","np":2,"cix":2,"bm":0,"ix":1,"mn":"ADBE Vector Group","hd":false}],"ip":0,"op":225,"st":0,"bm":0},{"ddd":0,"ind":28,"ty":3,"nm":"Clip 188","parent":25,"sr":1,"ks":{"o":{"a":0,"k":100,"ix":11},"r":{"a":0,"k":0,"ix":10},"p":{"a":0,"k":[8.339,11.42,0],"ix":2},"a":{"a":0,"k":[0,0,0],"ix":1},"s":{"a":0,"k":[100,100,100],"ix":6}},"ao":0,"ip":0,"op":225,"st":0,"bm":0},{"ddd":0,"ind":29,"ty":4,"nm":"Fill 186","sr":1,"ks":{"o":{"a":0,"k":100,"ix":11},"r":{"a":0,"k":0,"ix":10},"p":{"a":0,"k":[137.268,349.673,0],"ix":2},"a":{"a":0,"k":[0,0,0],"ix":1},"s":{"a":0,"k":[100,100,100],"ix":6}},"ao":0,"shapes":[{"ty":"gr","it":[{"ind":0,"ty":"sh","ix":1,"ks":{"a":0,"k":{"i":[[0,0],[0,0],[0.94,-1.13],[0,1.13],[0,0],[0,0],[0,0]],"o":[[0,0],[0,0],[0,0],[0,-1.14],[0,0],[0,0],[0,0]],"v":[[-2.227,-11.066],[-2.227,5.394],[7.713,11.064],[-6.017,9.934],[-5.537,4.824],[-7.767,-10.156],[-2.227,-11.066]],"c":false},"ix":2},"nm":"Path 1","mn":"ADBE Vector Shape - Group","hd":false},{"ty":"fl","c":{"a":0,"k":[1,0.803921997547,0.635294020176,1],"ix":4},"o":{"a":0,"k":100,"ix":5},"r":1,"bm":0,"nm":"Fill 1","mn":"ADBE Vector Graphic - Fill","hd":false},{"ty":"tr","p":{"a":0,"k":[0,0],"ix":2},"a":{"a":0,"k":[0,0],"ix":1},"s":{"a":0,"k":[100,100],"ix":3},"r":{"a":0,"k":0,"ix":6},"o":{"a":0,"k":100,"ix":7},"sk":{"a":0,"k":0,"ix":4},"sa":{"a":0,"k":0,"ix":5},"nm":"Transform"}],"nm":"Fill 186","np":2,"cix":2,"bm":0,"ix":1,"mn":"ADBE Vector Group","hd":false}],"ip":0,"op":225,"st":0,"bm":0},{"ddd":0,"ind":30,"ty":3,"nm":"▽ Group 185","sr":1,"ks":{"o":{"a":0,"k":100,"ix":11},"r":{"a":0,"k":0,"ix":10},"p":{"a":0,"k":[99.526,352.133,0],"ix":2},"a":{"a":0,"k":[5.838,12.375,0],"ix":1},"s":{"a":0,"k":[100,100,100],"ix":6}},"ao":0,"ip":0,"op":225,"st":0,"bm":0},{"ddd":0,"ind":31,"ty":4,"nm":"▨ Clip 185","parent":33,"td":1,"sr":1,"ks":{"o":{"a":0,"k":100,"ix":11},"r":{"a":0,"k":0,"ix":10},"p":{"a":0,"k":[0,0,0],"ix":2},"a":{"a":0,"k":[0,0,0],"ix":1},"s":{"a":0,"k":[100,100,100],"ix":6}},"ao":0,"shapes":[{"ty":"gr","it":[{"ind":0,"ty":"sh","ix":1,"ks":{"a":0,"k":{"i":[[0,0],[0,0],[0,0],[1.89,-1.13],[0.48,1.14],[-0.95,0.56],[0,0],[0,0],[0,0]],"o":[[0,0],[0,0],[0,0],[-1.9,1.14],[-0.47,-1.13],[0.95,-0.57],[0,0],[0,0],[0,0]],"v":[[5.508,-7.996],[-0.152,1.274],[0.788,8.654],[4.108,10.924],[-2.052,10.924],[-5.362,-1.556],[-2.052,-3.266],[1.268,-11.776],[5.508,-7.996]],"c":false},"ix":2},"nm":"Path 1","mn":"ADBE Vector Shape - Group","hd":false},{"ty":"tr","p":{"a":0,"k":[0,0],"ix":2},"a":{"a":0,"k":[0,0],"ix":1},"s":{"a":0,"k":[100,100],"ix":3},"r":{"a":0,"k":0,"ix":6},"o":{"a":0,"k":100,"ix":7},"sk":{"a":0,"k":0,"ix":4},"sa":{"a":0,"k":0,"ix":5},"nm":"Transform"}],"nm":"Clip 184","np":1,"cix":2,"bm":0,"ix":1,"mn":"ADBE Vector Group","hd":false},{"ty":"fl","c":{"a":0,"k":[1,0,0,1],"ix":4},"o":{"a":0,"k":100,"ix":5},"r":1,"bm":0,"nm":"Fill 1","mn":"ADBE Vector Graphic - Fill","hd":false}],"ip":0,"op":225,"st":0,"bm":0},{"ddd":0,"ind":32,"ty":4,"nm":"Fill 183","parent":30,"tt":1,"sr":1,"ks":{"o":{"a":0,"k":100,"ix":11},"r":{"a":0,"k":0,"ix":10},"p":{"a":0,"k":[5.388,16.441,0],"ix":2},"a":{"a":0,"k":[0,0,0],"ix":1},"s":{"a":0,"k":[100,100,100],"ix":6}},"ao":0,"shapes":[{"ty":"gr","it":[{"ind":0,"ty":"sh","ix":1,"ks":{"a":0,"k":{"i":[[0,0],[0,0],[0,1.71],[2.37,0],[0,0],[0,0],[0,0],[0,0],[0,0],[0,0]],"o":[[0,0],[0,0],[0,-1.7],[-2.36,0],[0,0],[0,0],[0,0],[0,0],[0,0],[0,0]],"v":[[0.945,-0.562],[0.475,-2.832],[-1.415,-4.542],[-3.315,-8.512],[-6.625,-1.702],[-4.255,5.678],[-1.895,8.508],[4.735,8.508],[6.625,5.108],[0.945,-0.562]],"c":false},"ix":2},"nm":"Path 1","mn":"ADBE Vector Shape - Group","hd":false},{"ty":"fl","c":{"a":0,"k":[0.129411995411,0.129411995411,0.129411995411,1],"ix":4},"o":{"a":0,"k":100,"ix":5},"r":1,"bm":0,"nm":"Fill 1","mn":"ADBE Vector Graphic - Fill","hd":false},{"ty":"tr","p":{"a":0,"k":[0,0],"ix":2},"a":{"a":0,"k":[0,0],"ix":1},"s":{"a":0,"k":[100,100],"ix":3},"r":{"a":0,"k":0,"ix":6},"o":{"a":0,"k":100,"ix":7},"sk":{"a":0,"k":0,"ix":4},"sa":{"a":0,"k":0,"ix":5},"nm":"Transform"}],"nm":"Fill 183","np":2,"cix":2,"bm":0,"ix":1,"mn":"ADBE Vector Group","hd":false}],"ip":0,"op":225,"st":0,"bm":0},{"ddd":0,"ind":33,"ty":3,"nm":"Clip 184","parent":30,"sr":1,"ks":{"o":{"a":0,"k":100,"ix":11},"r":{"a":0,"k":0,"ix":10},"p":{"a":0,"k":[6.017,12.326,0],"ix":2},"a":{"a":0,"k":[0,0,0],"ix":1},"s":{"a":0,"k":[100,100,100],"ix":6}},"ao":0,"ip":0,"op":225,"st":0,"bm":0},{"ddd":0,"ind":34,"ty":4,"nm":"Fill 182","sr":1,"ks":{"o":{"a":0,"k":100,"ix":11},"r":{"a":0,"k":0,"ix":10},"p":{"a":0,"k":[99.705,352.084,0],"ix":2},"a":{"a":0,"k":[0,0,0],"ix":1},"s":{"a":0,"k":[100,100,100],"ix":6}},"ao":0,"shapes":[{"ty":"gr","it":[{"ind":0,"ty":"sh","ix":1,"ks":{"a":0,"k":{"i":[[0,0],[0,0],[0,0],[1.89,-1.13],[0.48,1.14],[-0.95,0.56],[0,0],[0,0],[0,0]],"o":[[0,0],[0,0],[0,0],[-1.9,1.14],[-0.47,-1.13],[0.95,-0.57],[0,0],[0,0],[0,0]],"v":[[5.508,-7.996],[-0.152,1.274],[0.788,8.654],[4.108,10.924],[-2.052,10.924],[-5.362,-1.556],[-2.052,-3.266],[1.268,-11.776],[5.508,-7.996]],"c":false},"ix":2},"nm":"Path 1","mn":"ADBE Vector Shape - Group","hd":false},{"ty":"fl","c":{"a":0,"k":[1,0.803921997547,0.635294020176,1],"ix":4},"o":{"a":0,"k":100,"ix":5},"r":1,"bm":0,"nm":"Fill 1","mn":"ADBE Vector Graphic - Fill","hd":false},{"ty":"tr","p":{"a":0,"k":[0,0],"ix":2},"a":{"a":0,"k":[0,0],"ix":1},"s":{"a":0,"k":[100,100],"ix":3},"r":{"a":0,"k":0,"ix":6},"o":{"a":0,"k":100,"ix":7},"sk":{"a":0,"k":0,"ix":4},"sa":{"a":0,"k":0,"ix":5},"nm":"Transform"}],"nm":"Fill 182","np":2,"cix":2,"bm":0,"ix":1,"mn":"ADBE Vector Group","hd":false}],"ip":0,"op":225,"st":0,"bm":0},{"ddd":0,"ind":35,"ty":4,"nm":"Fill 109","sr":1,"ks":{"o":{"a":0,"k":100,"ix":11},"r":{"a":0,"k":0,"ix":10},"p":{"a":0,"k":[98.817,244.641,0],"ix":2},"a":{"a":0,"k":[0,0,0],"ix":1},"s":{"a":0,"k":[100,100,100],"ix":6}},"ao":0,"shapes":[{"ty":"gr","it":[{"ind":0,"ty":"sh","ix":1,"ks":{"a":0,"k":{"i":[[0,0],[-3.29,0.93],[0,0],[8.87,-4.99]],"o":[[0,0],[3.27,-0.92],[0,0],[0,0]],"v":[[-5.867,-0.523],[-0.297,0.387],[5.863,2.207],[-5.867,-0.523]],"c":false},"ix":2},"nm":"Path 1","mn":"ADBE Vector Shape - Group","hd":false},{"ty":"fl","c":{"a":0,"k":[0.274610996246,0.337015002966,0.585318028927,1],"ix":4},"o":{"a":0,"k":100,"ix":5},"r":1,"bm":0,"nm":"Fill 1","mn":"ADBE Vector Graphic - Fill","hd":false},{"ty":"tr","p":{"a":0,"k":[0,0],"ix":2},"a":{"a":0,"k":[0,0],"ix":1},"s":{"a":0,"k":[100,100],"ix":3},"r":{"a":0,"k":0,"ix":6},"o":{"a":0,"k":100,"ix":7},"sk":{"a":0,"k":0,"ix":4},"sa":{"a":0,"k":0,"ix":5},"nm":"Transform"}],"nm":"Fill 109","np":2,"cix":2,"bm":0,"ix":1,"mn":"ADBE Vector Group","hd":false}],"ip":0,"op":225,"st":0,"bm":0},{"ddd":0,"ind":36,"ty":4,"nm":"▨ Clip 146","parent":39,"td":1,"sr":1,"ks":{"o":{"a":0,"k":100,"ix":11},"r":{"a":0,"k":0,"ix":10},"p":{"a":0,"k":[0,0,0],"ix":2},"a":{"a":0,"k":[0,0,0],"ix":1},"s":{"a":0,"k":[100,100,100],"ix":6}},"ao":0,"shapes":[{"ty":"gr","it":[{"ind":0,"ty":"sh","ix":1,"ks":{"a":0,"k":{"i":[[0,0],[0,0],[0,0],[0,0]],"o":[[0,0],[0,0],[0,0],[0,0]],"v":[[-46.054,-91.184],[-46.054,91.186],[46.056,91.186],[46.056,-91.184]],"c":true},"ix":2},"nm":"Path 1","mn":"ADBE Vector Shape - Group","hd":false},{"ty":"rd","nm":"Round Corners 1","r":{"a":0,"k":7.8,"ix":1},"ix":2,"mn":"ADBE Vector Filter - RC","hd":false},{"ty":"fl","c":{"a":0,"k":[1,1,1,1],"ix":4},"o":{"a":0,"k":100,"ix":5},"r":1,"bm":0,"nm":"Fill 1","mn":"ADBE Vector Graphic - Fill","hd":false},{"ty":"tr","p":{"a":0,"k":[0,0],"ix":2},"a":{"a":0,"k":[0,0],"ix":1},"s":{"a":0,"k":[100,100],"ix":3},"r":{"a":0,"k":0,"ix":6},"o":{"a":0,"k":100,"ix":7},"sk":{"a":0,"k":0,"ix":4},"sa":{"a":0,"k":0,"ix":5},"nm":"Transform"}],"nm":"Clip 145","np":3,"cix":2,"bm":0,"ix":1,"mn":"ADBE Vector Group","hd":false},{"ty":"fl","c":{"a":0,"k":[1,0,0,1],"ix":4},"o":{"a":0,"k":100,"ix":5},"r":1,"bm":0,"nm":"Fill 1","mn":"ADBE Vector Graphic - Fill","hd":false}],"ip":0,"op":225,"st":0,"bm":0},{"ddd":0,"ind":37,"ty":4,"nm":"Rectangle","tt":1,"sr":1,"ks":{"o":{"a":0,"k":100,"ix":11},"r":{"a":0,"k":0,"ix":10},"p":{"a":0,"k":[199.541,172.211,0],"ix":2},"a":{"a":0,"k":[0,0,0],"ix":1},"s":{"a":0,"k":[100,100,100],"ix":6}},"ao":0,"shapes":[{"ty":"gr","it":[{"ty":"rc","d":1,"s":{"a":0,"k":[7.784,7.816],"ix":2},"p":{"a":0,"k":[0,0],"ix":3},"r":{"a":0,"k":3.9,"ix":4},"nm":"Rectangle Path 1","mn":"ADBE Vector Shape - Rect","hd":false},{"ty":"fl","c":{"a":0,"k":[0.129411995411,0.129411995411,0.129411995411,1],"ix":4},"o":{"a":0,"k":100,"ix":5},"r":1,"bm":0,"nm":"Fill 1","mn":"ADBE Vector Graphic - Fill","hd":false},{"ty":"tr","p":{"a":0,"k":[0,0],"ix":2},"a":{"a":0,"k":[0,0],"ix":1},"s":{"a":0,"k":[100,100],"ix":3},"r":{"a":0,"k":0,"ix":6},"o":{"a":0,"k":100,"ix":7},"sk":{"a":0,"k":0,"ix":4},"sa":{"a":0,"k":0,"ix":5},"nm":"Transform"}],"nm":"Rectangle","np":2,"cix":2,"bm":0,"ix":1,"mn":"ADBE Vector Group","hd":false}],"ip":0,"op":225,"st":0,"bm":0},{"ddd":0,"ind":38,"ty":4,"nm":"Shape Layer 2","sr":1,"ks":{"o":{"a":0,"k":100,"ix":11},"r":{"a":0,"k":0,"ix":10},"p":{"a":0,"k":[180,320,0],"ix":2},"a":{"a":0,"k":[0,0,0],"ix":1},"s":{"a":0,"k":[98.178,97.854,100],"ix":6}},"ao":0,"shapes":[{"ty":"gr","it":[{"ty":"rc","d":1,"s":{"a":0,"k":[92.111,103.447],"ix":2},"p":{"a":0,"k":[0,0],"ix":3},"r":{"a":0,"k":4,"ix":4},"nm":"Rectangle Path 1","mn":"ADBE Vector Shape - Rect","hd":false},{"ty":"fl","c":{"a":0,"k":[1,1,1,1],"ix":4},"o":{"a":0,"k":100,"ix":5},"r":1,"bm":0,"nm":"Fill 1","mn":"ADBE Vector Graphic - Fill","hd":false},{"ty":"tr","p":{"a":0,"k":[18.823,-58.604],"ix":2},"a":{"a":0,"k":[0,0],"ix":1},"s":{"a":0,"k":[100.458,179.522],"ix":3},"r":{"a":0,"k":0,"ix":6},"o":{"a":0,"k":100,"ix":7},"sk":{"a":0,"k":0,"ix":4},"sa":{"a":0,"k":0,"ix":5},"nm":"Transform"}],"nm":"Rectangle 1","np":3,"cix":2,"bm":0,"ix":1,"mn":"ADBE Vector Group","hd":false}],"ip":0,"op":225,"st":0,"bm":0},{"ddd":0,"ind":39,"ty":3,"nm":"Clip 145","sr":1,"ks":{"o":{"a":0,"k":100,"ix":11},"r":{"a":0,"k":0,"ix":10},"p":{"a":0,"k":[198.892,262.092,0],"ix":2},"a":{"a":0,"k":[0,0,0],"ix":1},"s":{"a":0,"k":[100,100,100],"ix":6}},"ao":0,"ip":0,"op":225,"st":0,"bm":0},{"ddd":0,"ind":40,"ty":4,"nm":"Fill 89","sr":1,"ks":{"o":{"a":0,"k":100,"ix":11},"r":{"a":0,"k":0,"ix":10},"p":{"a":0,"k":[198.892,262.743,0],"ix":2},"a":{"a":0,"k":[0,0,0],"ix":1},"s":{"a":0,"k":[100,100,100],"ix":6}},"ao":0,"shapes":[{"ty":"gr","it":[{"ind":0,"ty":"sh","ix":1,"ks":{"a":0,"k":{"i":[[0,0],[0,0],[0,5.98],[0,0],[-4.9,0],[0,0],[0,-5.98],[0,0],[4.9,0]],"o":[[0,0],[-4.9,0],[0,0],[0,-5.98],[0,0],[4.9,0],[0,0],[0,5.98],[0,0]],"v":[[41.064,95.747],[-41.066,95.747],[-49.946,84.917],[-49.946,-84.913],[-41.066,-95.743],[41.064,-95.743],[49.944,-84.913],[49.944,84.917],[41.064,95.747]],"c":false},"ix":2},"nm":"Path 1","mn":"ADBE Vector Shape - Group","hd":false},{"ty":"fl","c":{"a":0,"k":[0.129411995411,0.129411995411,0.129411995411,1],"ix":4},"o":{"a":0,"k":100,"ix":5},"r":1,"bm":0,"nm":"Fill 1","mn":"ADBE Vector Graphic - Fill","hd":false},{"ty":"tr","p":{"a":0,"k":[0,0],"ix":2},"a":{"a":0,"k":[0,0],"ix":1},"s":{"a":0,"k":[100,100],"ix":3},"r":{"a":0,"k":0,"ix":6},"o":{"a":0,"k":100,"ix":7},"sk":{"a":0,"k":0,"ix":4},"sa":{"a":0,"k":0,"ix":5},"nm":"Transform"}],"nm":"Fill 89","np":2,"cix":2,"bm":0,"ix":1,"mn":"ADBE Vector Group","hd":false}],"ip":0,"op":225,"st":0,"bm":0},{"ddd":0,"ind":41,"ty":4,"nm":"Combined Shape","sr":1,"ks":{"o":{"a":0,"k":100,"ix":11},"r":{"a":0,"k":0,"ix":10},"p":{"a":0,"k":[170.913,357.836,0],"ix":2},"a":{"a":0,"k":[0,0,0],"ix":1},"s":{"a":0,"k":[100,100,100],"ix":6}},"ao":0,"shapes":[{"ty":"gr","it":[{"d":1,"ty":"el","s":{"a":0,"k":[159.568,14.329],"ix":2},"p":{"a":0,"k":[15.006,0],"ix":3},"nm":"Ellipse Path 1","mn":"ADBE Vector Shape - Ellipse","hd":false},{"ind":1,"ty":"sh","ix":2,"ks":{"a":0,"k":{"i":[[0,0],[0,2.34],[-11.71,0.75],[-0.22,-0.54],[-1.24,0],[-0.95,0.57],[0,0],[0,0],[-6.33,0],[0,-2.35],[22.95,0]],"o":[[-22.96,0],[0,-1.52],[0.86,2.75],[0.24,0.57],[1.24,0],[1.89,-1.14],[0,0],[5.37,-0.26],[22.95,0],[0,2.34],[0,0]],"v":[[-53.22,7.033],[-94.79,2.793],[-75.3,-0.807],[-73.26,5.173],[-70.71,6.023],[-67.1,5.173],[-70.42,2.903],[-70.92,-1.057],[-53.22,-1.457],[-11.66,2.793],[-53.22,7.033]],"c":false},"ix":2},"nm":"Path 1","mn":"ADBE Vector Shape - Group","hd":false},{"ty":"mm","mm":2,"nm":"Merge Paths 1","mn":"ADBE Vector Filter - Merge","hd":false},{"ty":"fl","c":{"a":0,"k":[0.129411995411,0.129411995411,0.129411995411,0.442634999752],"ix":4},"o":{"a":0,"k":44,"ix":5},"r":1,"bm":0,"nm":"Fill 1","mn":"ADBE Vector Graphic - Fill","hd":false},{"ty":"tr","p":{"a":0,"k":[0,0],"ix":2},"a":{"a":0,"k":[0,0],"ix":1},"s":{"a":0,"k":[100,100],"ix":3},"r":{"a":0,"k":0,"ix":6},"o":{"a":0,"k":100,"ix":7},"sk":{"a":0,"k":0,"ix":4},"sa":{"a":0,"k":0,"ix":5},"nm":"Transform"}],"nm":"Combined Shape","np":4,"cix":2,"bm":0,"ix":1,"mn":"ADBE Vector Group","hd":false}],"ip":0,"op":225,"st":0,"bm":0},{"ddd":0,"ind":42,"ty":4,"nm":"Fill 216","sr":1,"ks":{"o":{"a":0,"k":100,"ix":11},"r":{"a":0,"k":0,"ix":10},"p":{"a":0,"k":[134.385,237.141,0],"ix":2},"a":{"a":0,"k":[0,0,0],"ix":1},"s":{"a":0,"k":[100,100,100],"ix":6}},"ao":0,"shapes":[{"ty":"gr","it":[{"ind":0,"ty":"sh","ix":1,"ks":{"a":0,"k":{"i":[[0,0],[8.04,-2.14],[4.02,-1.78],[-3.33,-2.75],[-0.84,0.42],[-1.46,1.46],[1.46,0.73]],"o":[[0,0],[-8.04,2.13],[-0.44,1.91],[6.31,-2.13],[1.46,-0.73],[1.46,-1.46],[-1.46,-0.74]],"v":[[15.738,-7.208],[-7.072,0.612],[-21.432,4.952],[-18.562,12.772],[-4.772,7.622],[21.148,-7.208],[19.048,-12.688]],"c":true},"ix":2},"nm":"Path 1","mn":"ADBE Vector Shape - Group","hd":false},{"ty":"fl","c":{"a":0,"k":[0.911175012589,0.702865004539,0.523716986179,1],"ix":4},"o":{"a":0,"k":100,"ix":5},"r":1,"bm":0,"nm":"Fill 1","mn":"ADBE Vector Graphic - Fill","hd":false},{"ty":"tr","p":{"a":0,"k":[0,0],"ix":2},"a":{"a":0,"k":[0,0],"ix":1},"s":{"a":0,"k":[100,100],"ix":3},"r":{"a":0,"k":13,"ix":6},"o":{"a":0,"k":100,"ix":7},"sk":{"a":0,"k":0,"ix":4},"sa":{"a":0,"k":0,"ix":5},"nm":"Transform"}],"nm":"Fill 216","np":2,"cix":2,"bm":0,"ix":1,"mn":"ADBE Vector Group","hd":false}],"ip":0,"op":225,"st":0,"bm":0}]}],"layers":[{"ddd":0,"ind":1,"ty":0,"nm":"Card 1","refId":"comp_0","sr":1,"ks":{"o":{"a":1,"k":[{"i":{"x":[0.833],"y":[0.833]},"o":{"x":[0.167],"y":[0.167]},"t":10,"s":[0]},{"t":15,"s":[100]}],"ix":11},"r":{"a":0,"k":0,"ix":10},"p":{"a":0,"k":[150,222,0],"ix":2},"a":{"a":0,"k":[180,320,0],"ix":1},"s":{"a":0,"k":[100,100,100],"ix":6}},"ao":0,"w":360,"h":640,"ip":10,"op":51,"st":10,"bm":0},{"ddd":0,"ind":2,"ty":0,"nm":"Card 2","refId":"comp_0","sr":1,"ks":{"o":{"a":1,"k":[{"i":{"x":[0.833],"y":[0.833]},"o":{"x":[0.167],"y":[0.167]},"t":18,"s":[0]},{"t":26,"s":[100]}],"ix":11},"r":{"a":0,"k":0,"ix":10},"p":{"a":1,"k":[{"i":{"x":0.833,"y":0.833},"o":{"x":0.167,"y":0.167},"t":0,"s":[150,222,0],"to":[0,0,0],"ti":[0,0,0]},{"i":{"x":0.833,"y":0.833},"o":{"x":0.167,"y":0.167},"t":18,"s":[150,222,0],"to":[0,7.333,0],"ti":[0,-7.333,0]},{"t":23,"s":[150,266,0]}],"ix":2},"a":{"a":0,"k":[180,320,0],"ix":1},"s":{"a":0,"k":[100,100,100],"ix":6}},"ao":0,"w":360,"h":640,"ip":18,"op":51,"st":18,"bm":0},{"ddd":0,"ind":3,"ty":0,"nm":"Card 3","refId":"comp_0","sr":1,"ks":{"o":{"a":1,"k":[{"i":{"x":[0.833],"y":[0.833]},"o":{"x":[0.167],"y":[0.167]},"t":26,"s":[0]},{"t":35,"s":[100]}],"ix":11},"r":{"a":0,"k":0,"ix":10},"p":{"a":1,"k":[{"i":{"x":0.833,"y":0.833},"o":{"x":0.167,"y":0.167},"t":0,"s":[150,264,0],"to":[0,0.333,0],"ti":[0,-7.667,0]},{"i":{"x":0.833,"y":0.833},"o":{"x":0.167,"y":0.167},"t":26,"s":[150,266,0],"to":[0,7.667,0],"ti":[0,-7.333,0]},{"t":31,"s":[150,310,0]}],"ix":2},"a":{"a":0,"k":[180,320,0],"ix":1},"s":{"a":0,"k":[100,100,100],"ix":6}},"ao":0,"w":360,"h":640,"ip":26,"op":51,"st":26,"bm":0},{"ddd":0,"ind":4,"ty":0,"nm":"Card 4","refId":"comp_0","sr":1,"ks":{"o":{"a":1,"k":[{"i":{"x":[0.833],"y":[0.833]},"o":{"x":[0.167],"y":[0.167]},"t":35,"s":[0]},{"t":43,"s":[100]}],"ix":11},"r":{"a":0,"k":0,"ix":10},"p":{"a":1,"k":[{"i":{"x":0.833,"y":0.833},"o":{"x":0.167,"y":0.167},"t":0,"s":[150,309,0],"to":[0,0.167,0],"ti":[0,-7.5,0]},{"i":{"x":0.833,"y":0.833},"o":{"x":0.167,"y":0.167},"t":35,"s":[150,310,0],"to":[0,7.5,0],"ti":[0,-7.333,0]},{"t":40,"s":[150,354,0]}],"ix":2},"a":{"a":0,"k":[180,320,0],"ix":1},"s":{"a":0,"k":[100,100,100],"ix":6}},"ao":0,"w":360,"h":640,"ip":35,"op":51,"st":35,"bm":0},{"ddd":0,"ind":5,"ty":0,"nm":"Phone","refId":"comp_1","sr":1,"ks":{"o":{"a":0,"k":100,"ix":11},"r":{"a":0,"k":0,"ix":10},"p":{"a":0,"k":[150,224,0],"ix":2},"a":{"a":0,"k":[180,320,0],"ix":1},"s":{"a":0,"k":[100,100,100],"ix":6}},"ao":0,"w":360,"h":640,"ip":0,"op":51,"st":0,"bm":0},{"ddd":0,"ind":6,"ty":4,"nm":"Shape 2","sr":1,"ks":{"o":{"a":0,"k":100,"ix":11},"r":{"a":0,"k":0,"ix":10},"p":{"a":0,"k":[83.487,180.593,0],"ix":2},"a":{"a":0,"k":[0,0,0],"ix":1},"s":{"a":0,"k":[100,100,100],"ix":6}},"ao":0,"shapes":[{"ty":"gr","it":[{"ind":0,"ty":"sh","ix":1,"ks":{"a":0,"k":{"i":[[0,0],[-4.1,0],[-9.54,0],[0,-1.75],[0,-5.91],[0,0],[0,0],[-0.41,0.6],[-11.28,3.7],[-9.72,-25.95],[1.21,-13.24],[6.68,-11.37],[19.27,1.59],[7.56,7.62],[0.75,1.02],[0,0],[0,0],[0,0],[0,0.56],[-0.07,45.85],[0.55,3.43],[5.8,1.07],[2.87,0.14],[0.02,1.44],[0.16,1.37]],"o":[[4.1,0],[9.55,0],[1.71,0],[0,5.91],[0,0],[0,0],[0.45,-0.61],[6.47,-9.74],[20.79,-6.71],[4.43,12.53],[-0.85,12.94],[-9.75,16.59],[-10.68,-1.06],[-0.86,-0.93],[0,0],[0,0],[0,0],[0,-0.6],[0,-45.85],[0.02,-3.47],[-0.99,-5.82],[-2.83,-0.5],[-1.5,0],[-0.02,-1.43],[0,0]],"v":[[-64.487,-82.195],[-52.207,-82.065],[-23.547,-82.065],[-21.307,-79.825],[-21.307,-62.095],[-21.307,-59.655],[-20.747,-59.405],[-19.417,-61.175],[6.443,-82.425],[59.233,-56.315],[64.103,-17.205],[53.793,19.845],[10.163,42.745],[-18.057,29.315],[-20.477,26.385],[-21.237,26.805],[-21.237,84.835],[-43.017,84.835],[-43.177,83.085],[-43.067,-54.465],[-43.867,-64.845],[-53.507,-74.515],[-62.067,-75.485],[-64.037,-77.545],[-64.487,-81.755]],"c":true},"ix":2},"nm":"Path 1","mn":"ADBE Vector Shape - Group","hd":false},{"ind":1,"ty":"sh","ix":2,"ks":{"a":0,"k":{"i":[[0,-10.75],[0,-10.99],[-0.94,-0.8],[-10,-1.59],[-6.03,5.75],[-1.5,6.21],[3.06,15.59],[4.56,6.81],[10.67,-3.02],[6.12,-8.97],[-0.07,-0.96]],"o":[[0,10.99],[0.07,1.22],[7.92,6.29],[7.93,1.05],[4.49,-4.55],[4.12,-15.35],[-1.25,-8.1],[-6.47,-9.18],[-10.43,3.07],[-0.47,0.84],[0,10.81]],"v":[[-21.367,-17.158],[-21.367,15.792],[-19.797,18.952],[7.543,30.972],[28.803,24.792],[37.953,8.342],[39.563,-38.678],[30.753,-61.328],[4.803,-70.868],[-20.787,-52.248],[-21.397,-49.488]],"c":true},"ix":2},"nm":"Path 2","mn":"ADBE Vector Shape - Group","hd":false},{"ty":"mm","mm":1,"nm":"Merge Paths 1","mn":"ADBE Vector Filter - Merge","hd":false},{"ty":"fl","c":{"a":0,"k":[0,0.396078431373,1,1],"ix":4},"o":{"a":0,"k":20,"ix":5},"r":1,"bm":0,"nm":"Fill 1","mn":"ADBE Vector Graphic - Fill","hd":false},{"ty":"tr","p":{"a":0,"k":[0,0],"ix":2},"a":{"a":0,"k":[0,0],"ix":1},"s":{"a":0,"k":[100,100],"ix":3},"r":{"a":0,"k":0,"ix":6},"o":{"a":0,"k":100,"ix":7},"sk":{"a":0,"k":0,"ix":4},"sa":{"a":0,"k":0,"ix":5},"nm":"Transform"}],"nm":"Shape","np":4,"cix":2,"bm":0,"ix":1,"mn":"ADBE Vector Group","hd":false}],"ip":0,"op":225,"st":0,"bm":0},{"ddd":0,"ind":7,"ty":4,"nm":"Shape","sr":1,"ks":{"o":{"a":0,"k":100,"ix":11},"r":{"a":0,"k":0,"ix":10},"p":{"a":0,"k":[210.526,132.726,0],"ix":2},"a":{"a":0,"k":[0,0,0],"ix":1},"s":{"a":0,"k":[100,100,100],"ix":6}},"ao":0,"shapes":[{"ty":"gr","it":[{"ind":0,"ty":"sh","ix":1,"ks":{"a":0,"k":{"i":[[0.92,0],[0,0],[0,0],[0,0],[-3.03,3.09],[-18.49,-5.18],[-5.31,-10.59],[-0.43,-9.78],[5.58,-13.72],[10.69,-6.11],[15.54,13.41],[1.48,1.3],[0.65,0.03],[0.11,-0.56],[0.76,-3.98],[0.47,0],[5.9,0],[0,0],[0,49.64],[0.6,4.71],[2.62,0.36],[4.17,0.65]],"o":[[0,0],[0,0],[0,0],[3.01,-3.63],[13.45,-13.79],[11.76,3.29],[4.3,8.8],[0.94,14.66],[-4.49,11.2],[-17.97,9.92],[-1.51,-1.3],[-0.48,-0.43],[-0.24,0],[-0.79,4.01],[-0.14,0.63],[-5.6,0],[0,0],[0,-49.64],[-0.11,-4.75],[-0.15,-2.65],[-4.06,-0.77],[-0.8,-0.11]],"v":[[-66.032,-84.006],[-66.032,-90.726],[-22.942,-90.726],[-22.942,-12.366],[-14.332,-22.626],[33.918,-35.626],[58.568,-13.246],[65.738,14.924],[59.938,57.744],[37.878,84.614],[-17.892,78.814],[-22.222,74.784],[-23.972,74.064],[-24.682,75.544],[-26.922,87.564],[-28.252,89.154],[-45.352,89.154],[-45.352,86.534],[-45.352,-62.386],[-46.422,-76.596],[-51.192,-81.766],[-63.482,-83.766]],"c":true},"ix":2},"nm":"Path 1","mn":"ADBE Vector Shape - Group","hd":false},{"ind":1,"ty":"sh","ix":2,"ks":{"a":0,"k":{"i":[[0,-10.68],[0,-10.97],[-0.66,-0.66],[-9.73,-1.79],[-5.61,15.6],[-0.03,8.33],[2.7,11.04],[4.86,4.73],[8.96,-1.7],[7,-8.11],[-0.08,-1.73]],"o":[[0,10.99],[-0.01,0.93],[7.8,6.07],[16.13,2.51],[2.63,-7.91],[0.66,-11.35],[-1.44,-6.63],[-7.17,-6.45],[-10.8,2.06],[-1.16,1.28],[0.02,10.68]],"v":[[-22.893,30.394],[-22.893,63.344],[-21.883,65.834],[4.807,77.804],[38.177,58.514],[42.207,33.994],[39.117,0.214],[29.457,-17.206],[4.807,-22.776],[-21.193,-6.366],[-22.873,-1.666]],"c":true},"ix":2},"nm":"Path 2","mn":"ADBE Vector Shape - Group","hd":false},{"ty":"mm","mm":1,"nm":"Merge Paths 1","mn":"ADBE Vector Filter - Merge","hd":false},{"ty":"fl","c":{"a":0,"k":[0,0.396078431373,1,1],"ix":4},"o":{"a":0,"k":20,"ix":5},"r":1,"bm":0,"nm":"Fill 1","mn":"ADBE Vector Graphic - Fill","hd":false},{"ty":"tr","p":{"a":0,"k":[0,0],"ix":2},"a":{"a":0,"k":[0,0],"ix":1},"s":{"a":0,"k":[100,100],"ix":3},"r":{"a":0,"k":0,"ix":6},"o":{"a":0,"k":100,"ix":7},"sk":{"a":0,"k":0,"ix":4},"sa":{"a":0,"k":0,"ix":5},"nm":"Transform"}],"nm":"Shape","np":4,"cix":2,"bm":0,"ix":1,"mn":"ADBE Vector Group","hd":false}],"ip":0,"op":225,"st":0,"bm":0}],"markers":[]}